README.rst
mkbrutus.py
setup.py
mkbrutus.egg-info/PKG-INFO
mkbrutus.egg-info/SOURCES.txt
mkbrutus.egg-info/dependency_links.txt
mkbrutus.egg-info/requires.txt
mkbrutus.egg-info/top_level.txt