Metadata-Version: 1.1
Name: mkbrutus
Version: 1.0.2a1
Summary: Password bruteforcer for MikroTik devices
Home-page: https://github.com/mkbrutusproject/mkbrutus
Author: Ramiro Caire
Author-email: ramiro.caire@gmail.com
License: AGPL
Keywords: mkbrutus Mikrotik RouterOS
Platform: UNKNOWN
Classifier: Development Status :: 3 - Alpha
Classifier: Programming Language :: Python :: 2
Classifier: Programming Language :: Python :: 2.6
Classifier: Programming Language :: Python :: 2.7
